[
	{"name": "Alexandro",
	 "year": 2222,
	 "id": "ale"},
	{"name": "Blue Eyes",
	 "year": 1111,
	 "id": "blu"},
	{"name": "Now or Never",
	 "year": 6666,
	 "id": "now"},
	{"name": "Machooo",
	 "year": 5555,
	 "id": "mac"},
	{"name": "Pascual",
	 "year": 3333,
	 "id": "pas"},
	{"name": "pablo",
	 "year": 4424,
	 "id": "pab"},
	{"name": "brauilio",
	 "year": 4454,
	 "id": "bra"},
	{"name": "mansoto",
	 "year": 4114,
	 "id": "man"},
	{"name": "peperulo",
	 "year": 3344,
	 "id": "pep"},
	{"name": "sarpado",
	 "year": 2244,
	 "id": "sar"},
	{"name": "dota",
	 "year": 2144,
	 "id": "dot"},
	{"name": "lol",
	 "year": 5544,
	 "id": "lol"}
]